<?xml version="1.0" encoding="UTF-8"?>
<persistence version="2.1" xmlns="http://xmlns.jcp.org/xml/ns/persistence" xmlns:xsi="http://www.w3.org/2001/XMLSchema-instance" xsi:schemaLocation="http://xmlns.jcp.org/xml/ns/persistence http://xmlns.jcp.org/xml/ns/persistence/persistence_2_1.xsd">
  <persistence-unit name="fr.insalyon_tp-dasi_1_jar_1.0-SNAPSHOTPU" transaction-type="RESOURCE_LOCAL">
    <provider>org.eclipse.persistence.jpa.PersistenceProvider</provider>
    <class>fr.insalyon.gustatif.metier.modele.Client</class>
    <class>fr.insalyon.gustatif.metier.modele.Produit</class>
    <class>fr.insalyon.gustatif.metier.modele.Restaurant</class>
    <properties>
      <property name="javax.persistence.jdbc.url" value="jdbc:derby://localhost:1527/tp-dasi_1"/>
      <property name="javax.persistence.jdbc.password" value="gustatif"/>
      <property name="javax.persistence.jdbc.driver" value="org.apache.derby.jdbc.ClientDriver"/>
      <property name="javax.persistence.jdbc.user" value="gustatif"/>
      <property name="javax.persistence.schema-generation.database.action" value="drop-and-create"/>
    </properties>
  </persistence-unit>
</persistence>
