<?xml version="1.0"?>
<simRes version="3.00" nbElements="28">
  <nbHubs>1</nbHubs>
  <nbSwitch>3</nbSwitch>
  <nbRouter>1</nbRouter>
  <nbCartesReseau>16</nbCartesReseau>
  <nbStations>11</nbStations>
  <dernierIdNoeud>16</dernierIdNoeud>
  <adrReseauInternet1>172.11.0.0</adrReseauInternet1>
  <adrReseauInternet2>172.12.0.0</adrReseauInternet2>
  <adrReseauInternet3>172.13.0.0</adrReseauInternet3>
  <adrReseauInternet4>172.14.0.0</adrReseauInternet4>
  <adrReseauInternet5>172.15.0.0</adrReseauInternet5>
  <iconeMessage />
  <station nomNoeud="PC1">
    <idNoeud>1</idNoeud>
    <infoNoeud />
    <nbPointsConnexion>1</nbPointsConnexion>
    <Location.X>5</Location.X>
    <Location.Y>258</Location.Y>
    <PosDemo.X>0</PosDemo.X>
    <PosDemo.Y>0</PosDemo.Y>
    <ConfigIpStation>
      <passerelle>10.0.0.1</passerelle>
      <routageActif>False</routageActif>
      <natPatActif>False</natPatActif>
      <carteQuiNat>-1</carteQuiNat>
      <serveurDns>0.0.0.0</serveurDns>
      <Routes nbLignes="4">
        <ligne nbValeurs="6" clef="01">
          <valeur>01</valeur>
          <valeur>10.0.0.2</valeur>
          <valeur>255.255.255.255</valeur>
          <valeur>10.0.0.2</valeur>
          <valeur>10.0.0.2</valeur>
          <valeur>1</valeur>
        </ligne>
        <ligne nbValeurs="6" clef="02">
          <valeur>02</valeur>
          <valeur>10.0.0.0</valeur>
          <valeur>255.255.255.0</valeur>
          <valeur>10.0.0.2</valeur>
          <valeur>10.0.0.2</valeur>
          <valeur>1</valeur>
        </ligne>
        <ligne nbValeurs="6" clef="03">
          <valeur>03</valeur>
          <valeur>10.0.0.255</valeur>
          <valeur>255.255.255.255</valeur>
          <valeur>10.0.0.2</valeur>
          <valeur>10.0.0.2</valeur>
          <valeur>1</valeur>
        </ligne>
        <ligne nbValeurs="6" clef="04">
          <valeur>04</valeur>
          <valeur>0.0.0.0</valeur>
          <valeur>0.0.0.0</valeur>
          <valeur>10.0.0.1</valeur>
          <valeur>10.0.0.2</valeur>
          <valeur>1</valeur>
        </ligne>
      </Routes>
      <CacheARP nbLignes="0" />
      <FichierHosts nbLignes="0" />
      <PortsEcoutes nbLignes="0" />
      <NatPat nbLignes="0" />
      <ReglesFiltrage nbLignes="0" />
    </ConfigIpStation>
    <AccesDistant>False</AccesDistant>
    <carte adresseMac="mac01">
      <PosDemoEmission.X>0</PosDemoEmission.X>
      <PosDemoEmission.Y>0</PosDemoEmission.Y>
      <ConfigIpCarte>
        <clientDhcp>False</clientDhcp>
        <adresse>10.0.0.2</adresse>
        <masque>255.255.255.0</masque>
      </ConfigIpCarte>
    </carte>
  </station>
  <station nomNoeud="Test1">
    <idNoeud>2</idNoeud>
    <infoNoeud />
    <nbPointsConnexion>1</nbPointsConnexion>
    <Location.X>71</Location.X>
    <Location.Y>257</Location.Y>
    <PosDemo.X>0</PosDemo.X>
    <PosDemo.Y>0</PosDemo.Y>
    <ConfigIpStation>
      <passerelle>10.2.0.1</passerelle>
      <routageActif>False</routageActif>
      <natPatActif>False</natPatActif>
      <carteQuiNat>-1</carteQuiNat>
      <serveurDns>0.0.0.0</serveurDns>
      <Routes nbLignes="4">
        <ligne nbValeurs="6" clef="01">
          <valeur>01</valeur>
          <valeur>10.2.0.4</valeur>
          <valeur>255.255.255.255</valeur>
          <valeur>10.2.0.4</valeur>
          <valeur>10.2.0.4</valeur>
          <valeur>1</valeur>
        </ligne>
        <ligne nbValeurs="6" clef="02">
          <valeur>02</valeur>
          <valeur>10.2.0.0</valeur>
          <valeur>255.255.255.0</valeur>
          <valeur>10.2.0.4</valeur>
          <valeur>10.2.0.4</valeur>
          <valeur>1</valeur>
        </ligne>
        <ligne nbValeurs="6" clef="03">
          <valeur>03</valeur>
          <valeur>10.2.0.255</valeur>
          <valeur>255.255.255.255</valeur>
          <valeur>10.2.0.4</valeur>
          <valeur>10.2.0.4</valeur>
          <valeur>1</valeur>
        </ligne>
        <ligne nbValeurs="6" clef="04">
          <valeur>04</valeur>
          <valeur>0.0.0.0</valeur>
          <valeur>0.0.0.0</valeur>
          <valeur>10.2.0.1</valeur>
          <valeur>10.2.0.4</valeur>
          <valeur>1</valeur>
        </ligne>
      </Routes>
      <CacheARP nbLignes="0" />
      <FichierHosts nbLignes="0" />
      <PortsEcoutes nbLignes="0" />
      <NatPat nbLignes="0" />
      <ReglesFiltrage nbLignes="0" />
    </ConfigIpStation>
    <AccesDistant>False</AccesDistant>
    <carte adresseMac="mac02">
      <PosDemoEmission.X>0</PosDemoEmission.X>
      <PosDemoEmission.Y>0</PosDemoEmission.Y>
      <ConfigIpCarte>
        <clientDhcp>False</clientDhcp>
        <adresse>10.2.0.4</adresse>
        <masque>255.255.255.0</masque>
      </ConfigIpCarte>
    </carte>
  </station>
  <station nomNoeud="MES">
    <idNoeud>3</idNoeud>
    <infoNoeud />
    <nbPointsConnexion>1</nbPointsConnexion>
    <Location.X>342</Location.X>
    <Location.Y>242</Location.Y>
    <PosDemo.X>0</PosDemo.X>
    <PosDemo.Y>0</PosDemo.Y>
    <ConfigIpStation>
      <passerelle>10.1.0.1</passerelle>
      <routageActif>False</routageActif>
      <natPatActif>False</natPatActif>
      <carteQuiNat>-1</carteQuiNat>
      <serveurDns>0.0.0.0</serveurDns>
      <Routes nbLignes="4">
        <ligne nbValeurs="6" clef="01">
          <valeur>01</valeur>
          <valeur>10.1.0.2</valeur>
          <valeur>255.255.255.255</valeur>
          <valeur>10.1.0.2</valeur>
          <valeur>10.1.0.2</valeur>
          <valeur>1</valeur>
        </ligne>
        <ligne nbValeurs="6" clef="02">
          <valeur>02</valeur>
          <valeur>10.1.0.0</valeur>
          <valeur>255.255.255.0</valeur>
          <valeur>10.1.0.2</valeur>
          <valeur>10.1.0.2</valeur>
          <valeur>1</valeur>
        </ligne>
        <ligne nbValeurs="6" clef="03">
          <valeur>03</valeur>
          <valeur>10.1.0.255</valeur>
          <valeur>255.255.255.255</valeur>
          <valeur>10.1.0.2</valeur>
          <valeur>10.1.0.2</valeur>
          <valeur>1</valeur>
        </ligne>
        <ligne nbValeurs="6" clef="04">
          <valeur>04</valeur>
          <valeur>0.0.0.0</valeur>
          <valeur>0.0.0.0</valeur>
          <valeur>10.1.0.1</valeur>
          <valeur>10.1.0.2</valeur>
          <valeur>1</valeur>
        </ligne>
      </Routes>
      <CacheARP nbLignes="0" />
      <FichierHosts nbLignes="0" />
      <PortsEcoutes nbLignes="0" />
      <NatPat nbLignes="0" />
      <ReglesFiltrage nbLignes="0" />
    </ConfigIpStation>
    <AccesDistant>False</AccesDistant>
    <carte adresseMac="mac03">
      <PosDemoEmission.X>0</PosDemoEmission.X>
      <PosDemoEmission.Y>0</PosDemoEmission.Y>
      <ConfigIpCarte>
        <clientDhcp>False</clientDhcp>
        <adresse>10.1.0.2</adresse>
        <masque>255.255.255.0</masque>
      </ConfigIpCarte>
    </carte>
  </station>
  <hub nomNoeud="hb1">
    <idNoeud>4</idNoeud>
    <infoNoeud />
    <nbPointsConnexion>7</nbPointsConnexion>
    <Location.X>22</Location.X>
    <Location.Y>199</Location.Y>
    <PosDemo.X>0</PosDemo.X>
    <PosDemo.Y>0</PosDemo.Y>
    <nbPortsNormaux>6</nbPortsNormaux>
    <nbPortsCascade>1</nbPortsCascade>
  </hub>
  <switch nomNoeud="sw1">
    <idNoeud>5</idNoeud>
    <infoNoeud />
    <nbPointsConnexion>7</nbPointsConnexion>
    <Location.X>135</Location.X>
    <Location.Y>140</Location.Y>
    <PosDemo.X>0</PosDemo.X>
    <PosDemo.Y>0</PosDemo.Y>
    <nbPortsNormaux>5</nbPortsNormaux>
    <nbPortsCascade>2</nbPortsCascade>
    <spanningTree>True</spanningTree>
    <nbPorts802.1q>0</nbPorts802.1q>
    <niveau_vlan>0</niveau_vlan>
    <typeSwitch>storeAndForward</typeSwitch>
    <PortSwitch numero="1">
      <PosDemoEmission.X>0</PosDemoEmission.X>
      <PosDemoEmission.Y>0</PosDemoEmission.Y>
    </PortSwitch>
    <PortSwitch numero="2">
      <PosDemoEmission.X>0</PosDemoEmission.X>
      <PosDemoEmission.Y>0</PosDemoEmission.Y>
    </PortSwitch>
    <PortSwitch numero="3">
      <PosDemoEmission.X>0</PosDemoEmission.X>
      <PosDemoEmission.Y>0</PosDemoEmission.Y>
    </PortSwitch>
    <PortSwitch numero="4">
      <PosDemoEmission.X>0</PosDemoEmission.X>
      <PosDemoEmission.Y>0</PosDemoEmission.Y>
    </PortSwitch>
    <PortSwitch numero="5">
      <PosDemoEmission.X>0</PosDemoEmission.X>
      <PosDemoEmission.Y>0</PosDemoEmission.Y>
    </PortSwitch>
    <PortSwitch numero="6">
      <PosDemoEmission.X>0</PosDemoEmission.X>
      <PosDemoEmission.Y>0</PosDemoEmission.Y>
    </PortSwitch>
    <PortSwitch numero="7">
      <PosDemoEmission.X>0</PosDemoEmission.X>
      <PosDemoEmission.Y>0</PosDemoEmission.Y>
    </PortSwitch>
    <table_port_vlan nbLignes="0" />
    <table_mac_vlan nbLignes="0" />
  </switch>
  <station nomNoeud="PC2">
    <idNoeud>6</idNoeud>
    <infoNoeud />
    <nbPointsConnexion>1</nbPointsConnexion>
    <Location.X>156</Location.X>
    <Location.Y>264</Location.Y>
    <PosDemo.X>0</PosDemo.X>
    <PosDemo.Y>0</PosDemo.Y>
    <ConfigIpStation>
      <passerelle>10.0.0.1</passerelle>
      <routageActif>False</routageActif>
      <natPatActif>False</natPatActif>
      <carteQuiNat>-1</carteQuiNat>
      <serveurDns>0.0.0.0</serveurDns>
      <Routes nbLignes="4">
        <ligne nbValeurs="6" clef="01">
          <valeur>01</valeur>
          <valeur>10.0.0.4</valeur>
          <valeur>255.255.255.255</valeur>
          <valeur>10.0.0.4</valeur>
          <valeur>10.0.0.4</valeur>
          <valeur>1</valeur>
        </ligne>
        <ligne nbValeurs="6" clef="02">
          <valeur>02</valeur>
          <valeur>10.0.0.0</valeur>
          <valeur>255.255.255.0</valeur>
          <valeur>10.0.0.4</valeur>
          <valeur>10.0.0.4</valeur>
          <valeur>1</valeur>
        </ligne>
        <ligne nbValeurs="6" clef="03">
          <valeur>03</valeur>
          <valeur>10.0.0.255</valeur>
          <valeur>255.255.255.255</valeur>
          <valeur>10.0.0.4</valeur>
          <valeur>10.0.0.4</valeur>
          <valeur>1</valeur>
        </ligne>
        <ligne nbValeurs="6" clef="04">
          <valeur>04</valeur>
          <valeur>0.0.0.0</valeur>
          <valeur>0.0.0.0</valeur>
          <valeur>10.0.0.1</valeur>
          <valeur>10.0.0.4</valeur>
          <valeur>1</valeur>
        </ligne>
      </Routes>
      <CacheARP nbLignes="0" />
      <FichierHosts nbLignes="0" />
      <PortsEcoutes nbLignes="0" />
      <NatPat nbLignes="0" />
      <ReglesFiltrage nbLignes="0" />
    </ConfigIpStation>
    <AccesDistant>False</AccesDistant>
    <carte adresseMac="mac04">
      <PosDemoEmission.X>0</PosDemoEmission.X>
      <PosDemoEmission.Y>0</PosDemoEmission.Y>
      <ConfigIpCarte>
        <clientDhcp>False</clientDhcp>
        <adresse>10.0.0.4</adresse>
        <masque>255.255.255.0</masque>
      </ConfigIpCarte>
    </carte>
  </station>
  <station nomNoeud="DNS">
    <idNoeud>7</idNoeud>
    <infoNoeud />
    <nbPointsConnexion>1</nbPointsConnexion>
    <Location.X>227</Location.X>
    <Location.Y>264</Location.Y>
    <PosDemo.X>0</PosDemo.X>
    <PosDemo.Y>0</PosDemo.Y>
    <ConfigIpStation>
      <passerelle>10.0.0.1</passerelle>
      <routageActif>False</routageActif>
      <natPatActif>False</natPatActif>
      <carteQuiNat>-1</carteQuiNat>
      <serveurDns>0.0.0.0</serveurDns>
      <Routes nbLignes="4">
        <ligne nbValeurs="6" clef="01">
          <valeur>01</valeur>
          <valeur>10.0.0.5</valeur>
          <valeur>255.255.255.255</valeur>
          <valeur>10.0.0.5</valeur>
          <valeur>10.0.0.5</valeur>
          <valeur>1</valeur>
        </ligne>
        <ligne nbValeurs="6" clef="02">
          <valeur>02</valeur>
          <valeur>10.0.0.0</valeur>
          <valeur>255.255.255.0</valeur>
          <valeur>10.0.0.5</valeur>
          <valeur>10.0.0.5</valeur>
          <valeur>1</valeur>
        </ligne>
        <ligne nbValeurs="6" clef="03">
          <valeur>03</valeur>
          <valeur>10.0.0.255</valeur>
          <valeur>255.255.255.255</valeur>
          <valeur>10.0.0.5</valeur>
          <valeur>10.0.0.5</valeur>
          <valeur>1</valeur>
        </ligne>
        <ligne nbValeurs="6" clef="04">
          <valeur>04</valeur>
          <valeur>0.0.0.0</valeur>
          <valeur>0.0.0.0</valeur>
          <valeur>10.0.0.1</valeur>
          <valeur>10.0.0.5</valeur>
          <valeur>1</valeur>
        </ligne>
      </Routes>
      <CacheARP nbLignes="0" />
      <FichierHosts nbLignes="0" />
      <PortsEcoutes nbLignes="0" />
      <NatPat nbLignes="0" />
      <ReglesFiltrage nbLignes="0" />
    </ConfigIpStation>
    <AccesDistant>False</AccesDistant>
    <carte adresseMac="mac05">
      <PosDemoEmission.X>0</PosDemoEmission.X>
      <PosDemoEmission.Y>0</PosDemoEmission.Y>
      <ConfigIpCarte>
        <clientDhcp>False</clientDhcp>
        <adresse>10.0.0.5</adresse>
        <masque>255.255.255.0</masque>
      </ConfigIpCarte>
    </carte>
  </station>
  <station nomNoeud="ERP">
    <idNoeud>8</idNoeud>
    <infoNoeud />
    <nbPointsConnexion>1</nbPointsConnexion>
    <Location.X>271</Location.X>
    <Location.Y>212</Location.Y>
    <PosDemo.X>0</PosDemo.X>
    <PosDemo.Y>0</PosDemo.Y>
    <ConfigIpStation>
      <passerelle>0.0.0.0</passerelle>
      <routageActif>False</routageActif>
      <natPatActif>False</natPatActif>
      <carteQuiNat>-1</carteQuiNat>
      <serveurDns>0.0.0.0</serveurDns>
      <Routes nbLignes="3">
        <ligne nbValeurs="6" clef="01">
          <valeur>01</valeur>
          <valeur>10.0.0.6</valeur>
          <valeur>255.255.255.255</valeur>
          <valeur>10.0.0.6</valeur>
          <valeur>10.0.0.6</valeur>
          <valeur>1</valeur>
        </ligne>
        <ligne nbValeurs="6" clef="02">
          <valeur>02</valeur>
          <valeur>10.0.0.0</valeur>
          <valeur>255.255.255.0</valeur>
          <valeur>10.0.0.6</valeur>
          <valeur>10.0.0.6</valeur>
          <valeur>1</valeur>
        </ligne>
        <ligne nbValeurs="6" clef="03">
          <valeur>03</valeur>
          <valeur>10.0.0.255</valeur>
          <valeur>255.255.255.255</valeur>
          <valeur>10.0.0.6</valeur>
          <valeur>10.0.0.6</valeur>
          <valeur>1</valeur>
        </ligne>
      </Routes>
      <CacheARP nbLignes="0" />
      <FichierHosts nbLignes="0" />
      <PortsEcoutes nbLignes="0" />
      <NatPat nbLignes="0" />
      <ReglesFiltrage nbLignes="0" />
    </ConfigIpStation>
    <AccesDistant>False</AccesDistant>
    <carte adresseMac="mac06">
      <PosDemoEmission.X>0</PosDemoEmission.X>
      <PosDemoEmission.Y>0</PosDemoEmission.Y>
      <ConfigIpCarte>
        <clientDhcp>False</clientDhcp>
        <adresse>10.0.0.6</adresse>
        <masque>255.255.255.0</masque>
      </ConfigIpCarte>
    </carte>
  </station>
  <station nomNoeud="Usinage 1">
    <idNoeud>9</idNoeud>
    <infoNoeud />
    <nbPointsConnexion>1</nbPointsConnexion>
    <Location.X>508</Location.X>
    <Location.Y>243</Location.Y>
    <PosDemo.X>0</PosDemo.X>
    <PosDemo.Y>0</PosDemo.Y>
    <ConfigIpStation>
      <passerelle>10.2.0.1</passerelle>
      <routageActif>False</routageActif>
      <natPatActif>False</natPatActif>
      <carteQuiNat>-1</carteQuiNat>
      <serveurDns>0.0.0.0</serveurDns>
      <Routes nbLignes="4">
        <ligne nbValeurs="6" clef="01">
          <valeur>01</valeur>
          <valeur>10.2.0.2</valeur>
          <valeur>255.255.255.255</valeur>
          <valeur>10.2.0.2</valeur>
          <valeur>10.2.0.2</valeur>
          <valeur>1</valeur>
        </ligne>
        <ligne nbValeurs="6" clef="02">
          <valeur>02</valeur>
          <valeur>10.2.0.0</valeur>
          <valeur>255.255.255.0</valeur>
          <valeur>10.2.0.2</valeur>
          <valeur>10.2.0.2</valeur>
          <valeur>1</valeur>
        </ligne>
        <ligne nbValeurs="6" clef="03">
          <valeur>03</valeur>
          <valeur>10.2.0.255</valeur>
          <valeur>255.255.255.255</valeur>
          <valeur>10.2.0.2</valeur>
          <valeur>10.2.0.2</valeur>
          <valeur>1</valeur>
        </ligne>
        <ligne nbValeurs="6" clef="04">
          <valeur>04</valeur>
          <valeur>0.0.0.0</valeur>
          <valeur>0.0.0.0</valeur>
          <valeur>10.2.0.1</valeur>
          <valeur>10.2.0.2</valeur>
          <valeur>1</valeur>
        </ligne>
      </Routes>
      <CacheARP nbLignes="0" />
      <FichierHosts nbLignes="0" />
      <PortsEcoutes nbLignes="0" />
      <NatPat nbLignes="0" />
      <ReglesFiltrage nbLignes="0" />
    </ConfigIpStation>
    <AccesDistant>False</AccesDistant>
    <carte adresseMac="mac07">
      <PosDemoEmission.X>0</PosDemoEmission.X>
      <PosDemoEmission.Y>0</PosDemoEmission.Y>
      <ConfigIpCarte>
        <clientDhcp>False</clientDhcp>
        <adresse>10.2.0.2</adresse>
        <masque>255.255.255.0</masque>
      </ConfigIpCarte>
    </carte>
  </station>
  <station nomNoeud="PC3">
    <idNoeud>10</idNoeud>
    <infoNoeud />
    <nbPointsConnexion>1</nbPointsConnexion>
    <Location.X>434</Location.X>
    <Location.Y>240</Location.Y>
    <PosDemo.X>0</PosDemo.X>
    <PosDemo.Y>0</PosDemo.Y>
    <ConfigIpStation>
      <passerelle>10.1.0.1</passerelle>
      <routageActif>False</routageActif>
      <natPatActif>False</natPatActif>
      <carteQuiNat>-1</carteQuiNat>
      <serveurDns>0.0.0.0</serveurDns>
      <Routes nbLignes="3">
        <ligne nbValeurs="6" clef="01">
          <valeur>01</valeur>
          <valeur>10.1.0.3</valeur>
          <valeur>255.255.255.255</valeur>
          <valeur>10.1.0.3</valeur>
          <valeur>10.1.0.3</valeur>
          <valeur>1</valeur>
        </ligne>
        <ligne nbValeurs="6" clef="02">
          <valeur>02</valeur>
          <valeur>10.1.0.0</valeur>
          <valeur>255.255.255.0</valeur>
          <valeur>10.1.0.3</valeur>
          <valeur>10.1.0.3</valeur>
          <valeur>1</valeur>
        </ligne>
        <ligne nbValeurs="6" clef="03">
          <valeur>03</valeur>
          <valeur>10.1.0.255</valeur>
          <valeur>255.255.255.255</valeur>
          <valeur>10.1.0.3</valeur>
          <valeur>10.1.0.3</valeur>
          <valeur>1</valeur>
        </ligne>
      </Routes>
      <CacheARP nbLignes="0" />
      <FichierHosts nbLignes="0" />
      <PortsEcoutes nbLignes="0" />
      <NatPat nbLignes="0" />
      <ReglesFiltrage nbLignes="0" />
    </ConfigIpStation>
    <AccesDistant>False</AccesDistant>
    <carte adresseMac="mac08">
      <PosDemoEmission.X>0</PosDemoEmission.X>
      <PosDemoEmission.Y>0</PosDemoEmission.Y>
      <ConfigIpCarte>
        <clientDhcp>False</clientDhcp>
        <adresse>10.1.0.3</adresse>
        <masque>255.255.255.0</masque>
      </ConfigIpCarte>
    </carte>
  </station>
  <station nomNoeud="Superviseur">
    <idNoeud>11</idNoeud>
    <infoNoeud />
    <nbPointsConnexion>1</nbPointsConnexion>
    <Location.X>590</Location.X>
    <Location.Y>241</Location.Y>
    <PosDemo.X>0</PosDemo.X>
    <PosDemo.Y>0</PosDemo.Y>
    <ConfigIpStation>
      <passerelle>10.2.0.1</passerelle>
      <routageActif>False</routageActif>
      <natPatActif>False</natPatActif>
      <carteQuiNat>-1</carteQuiNat>
      <serveurDns>0.0.0.0</serveurDns>
      <Routes nbLignes="4">
        <ligne nbValeurs="6" clef="01">
          <valeur>01</valeur>
          <valeur>10.2.0.3</valeur>
          <valeur>255.255.255.255</valeur>
          <valeur>10.2.0.3</valeur>
          <valeur>10.2.0.3</valeur>
          <valeur>1</valeur>
        </ligne>
        <ligne nbValeurs="6" clef="02">
          <valeur>02</valeur>
          <valeur>10.0.0.0</valeur>
          <valeur>255.0.0.0</valeur>
          <valeur>10.2.0.3</valeur>
          <valeur>10.2.0.3</valeur>
          <valeur>1</valeur>
        </ligne>
        <ligne nbValeurs="6" clef="03">
          <valeur>03</valeur>
          <valeur>10.255.255.255</valeur>
          <valeur>255.255.255.255</valeur>
          <valeur>10.2.0.3</valeur>
          <valeur>10.2.0.3</valeur>
          <valeur>1</valeur>
        </ligne>
        <ligne nbValeurs="6" clef="04">
          <valeur>04</valeur>
          <valeur>0.0.0.0</valeur>
          <valeur>0.0.0.0</valeur>
          <valeur>10.2.0.1</valeur>
          <valeur>10.2.0.3</valeur>
          <valeur>1</valeur>
        </ligne>
      </Routes>
      <CacheARP nbLignes="0" />
      <FichierHosts nbLignes="0" />
      <PortsEcoutes nbLignes="0" />
      <NatPat nbLignes="0" />
      <ReglesFiltrage nbLignes="0" />
    </ConfigIpStation>
    <AccesDistant>False</AccesDistant>
    <carte adresseMac="mac09">
      <PosDemoEmission.X>0</PosDemoEmission.X>
      <PosDemoEmission.Y>0</PosDemoEmission.Y>
      <ConfigIpCarte>
        <clientDhcp>False</clientDhcp>
        <adresse>10.2.0.3</adresse>
        <masque>255.0.0.0</masque>
      </ConfigIpCarte>
    </carte>
  </station>
  <switch nomNoeud="sw2">
    <idNoeud>14</idNoeud>
    <infoNoeud />
    <nbPointsConnexion>7</nbPointsConnexion>
    <Location.X>350</Location.X>
    <Location.Y>143</Location.Y>
    <PosDemo.X>0</PosDemo.X>
    <PosDemo.Y>0</PosDemo.Y>
    <nbPortsNormaux>4</nbPortsNormaux>
    <nbPortsCascade>3</nbPortsCascade>
    <spanningTree>True</spanningTree>
    <nbPorts802.1q>0</nbPorts802.1q>
    <niveau_vlan>0</niveau_vlan>
    <typeSwitch>storeAndForward</typeSwitch>
    <PortSwitch numero="1">
      <PosDemoEmission.X>0</PosDemoEmission.X>
      <PosDemoEmission.Y>0</PosDemoEmission.Y>
    </PortSwitch>
    <PortSwitch numero="2">
      <PosDemoEmission.X>0</PosDemoEmission.X>
      <PosDemoEmission.Y>0</PosDemoEmission.Y>
    </PortSwitch>
    <PortSwitch numero="3">
      <PosDemoEmission.X>0</PosDemoEmission.X>
      <PosDemoEmission.Y>0</PosDemoEmission.Y>
    </PortSwitch>
    <PortSwitch numero="4">
      <PosDemoEmission.X>0</PosDemoEmission.X>
      <PosDemoEmission.Y>0</PosDemoEmission.Y>
    </PortSwitch>
    <PortSwitch numero="5">
      <PosDemoEmission.X>0</PosDemoEmission.X>
      <PosDemoEmission.Y>0</PosDemoEmission.Y>
    </PortSwitch>
    <PortSwitch numero="6">
      <PosDemoEmission.X>0</PosDemoEmission.X>
      <PosDemoEmission.Y>0</PosDemoEmission.Y>
    </PortSwitch>
    <PortSwitch numero="7">
      <PosDemoEmission.X>0</PosDemoEmission.X>
      <PosDemoEmission.Y>0</PosDemoEmission.Y>
    </PortSwitch>
    <table_port_vlan nbLignes="0" />
    <table_mac_vlan nbLignes="0" />
  </switch>
  <switch nomNoeud="sw3">
    <idNoeud>15</idNoeud>
    <infoNoeud />
    <nbPointsConnexion>7</nbPointsConnexion>
    <Location.X>552</Location.X>
    <Location.Y>143</Location.Y>
    <PosDemo.X>0</PosDemo.X>
    <PosDemo.Y>0</PosDemo.Y>
    <nbPortsNormaux>4</nbPortsNormaux>
    <nbPortsCascade>3</nbPortsCascade>
    <spanningTree>True</spanningTree>
    <nbPorts802.1q>0</nbPorts802.1q>
    <niveau_vlan>0</niveau_vlan>
    <typeSwitch>storeAndForward</typeSwitch>
    <PortSwitch numero="1">
      <PosDemoEmission.X>0</PosDemoEmission.X>
      <PosDemoEmission.Y>0</PosDemoEmission.Y>
    </PortSwitch>
    <PortSwitch numero="2">
      <PosDemoEmission.X>0</PosDemoEmission.X>
      <PosDemoEmission.Y>0</PosDemoEmission.Y>
    </PortSwitch>
    <PortSwitch numero="3">
      <PosDemoEmission.X>0</PosDemoEmission.X>
      <PosDemoEmission.Y>0</PosDemoEmission.Y>
    </PortSwitch>
    <PortSwitch numero="4">
      <PosDemoEmission.X>0</PosDemoEmission.X>
      <PosDemoEmission.Y>0</PosDemoEmission.Y>
    </PortSwitch>
    <PortSwitch numero="5">
      <PosDemoEmission.X>0</PosDemoEmission.X>
      <PosDemoEmission.Y>0</PosDemoEmission.Y>
    </PortSwitch>
    <PortSwitch numero="6">
      <PosDemoEmission.X>0</PosDemoEmission.X>
      <PosDemoEmission.Y>0</PosDemoEmission.Y>
    </PortSwitch>
    <PortSwitch numero="7">
      <PosDemoEmission.X>0</PosDemoEmission.X>
      <PosDemoEmission.Y>0</PosDemoEmission.Y>
    </PortSwitch>
    <table_port_vlan nbLignes="0" />
    <table_mac_vlan nbLignes="0" />
  </switch>
  <router nomNoeud="rt1">
    <idNoeud>16</idNoeud>
    <infoNoeud />
    <nbPointsConnexion>5</nbPointsConnexion>
    <Location.X>270</Location.X>
    <Location.Y>45</Location.Y>
    <PosDemo.X>0</PosDemo.X>
    <PosDemo.Y>0</PosDemo.Y>
    <nbCartes>3</nbCartes>
    <nbDistants>2</nbDistants>
    <ConfigIpStation>
      <passerelle>0.0.0.0</passerelle>
      <routageActif>True</routageActif>
      <natPatActif>False</natPatActif>
      <carteQuiNat>-1</carteQuiNat>
      <serveurDns>0.0.0.0</serveurDns>
      <Routes nbLignes="3">
        <ligne nbValeurs="6" clef="01">
          <valeur>01</valeur>
          <valeur>10.0.0.0</valeur>
          <valeur>255.255.255.0</valeur>
          <valeur>10.0.0.1</valeur>
          <valeur>10.0.0.1</valeur>
          <valeur>1</valeur>
        </ligne>
        <ligne nbValeurs="6" clef="02">
          <valeur>02</valeur>
          <valeur>10.1.0.0</valeur>
          <valeur>255.255.255.0</valeur>
          <valeur>10.1.0.1</valeur>
          <valeur>10.1.0.1</valeur>
          <valeur>1</valeur>
        </ligne>
        <ligne nbValeurs="6" clef="03">
          <valeur>03</valeur>
          <valeur>10.2.0.0</valeur>
          <valeur>255.255.255.0</valeur>
          <valeur>10.2.0.1</valeur>
          <valeur>10.2.0.1</valeur>
          <valeur>1</valeur>
        </ligne>
      </Routes>
      <CacheARP nbLignes="0" />
      <FichierHosts nbLignes="0" />
      <PortsEcoutes nbLignes="0" />
      <NatPat nbLignes="0" />
      <ReglesFiltrage nbLignes="0" />
    </ConfigIpStation>
    <carte adresseMac="mac12">
      <PosDemoEmission.X>0</PosDemoEmission.X>
      <PosDemoEmission.Y>0</PosDemoEmission.Y>
      <ConfigIpCarte>
        <clientDhcp>False</clientDhcp>
        <adresse>10.0.0.1</adresse>
        <masque>255.255.255.0</masque>
      </ConfigIpCarte>
    </carte>
    <carte adresseMac="mac13">
      <PosDemoEmission.X>0</PosDemoEmission.X>
      <PosDemoEmission.Y>0</PosDemoEmission.Y>
      <ConfigIpCarte>
        <clientDhcp>False</clientDhcp>
        <adresse>10.1.0.1</adresse>
        <masque>255.255.255.0</masque>
      </ConfigIpCarte>
    </carte>
    <carte adresseMac="mac14">
      <PosDemoEmission.X>0</PosDemoEmission.X>
      <PosDemoEmission.Y>0</PosDemoEmission.Y>
      <ConfigIpCarte>
        <clientDhcp>False</clientDhcp>
        <adresse>10.2.0.1</adresse>
        <masque>255.255.255.0</masque>
      </ConfigIpCarte>
    </carte>
    <carteAccesDistant adresseMac="mac15">
      <ConfigIpCarte>
        <clientDhcp>False</clientDhcp>
        <adresse>0.0.0.0</adresse>
        <masque>0.0.0.0</masque>
      </ConfigIpCarte>
    </carteAccesDistant>
    <carteAccesDistant adresseMac="mac16">
      <ConfigIpCarte>
        <clientDhcp>False</clientDhcp>
        <adresse>0.0.0.0</adresse>
        <masque>0.0.0.0</masque>
      </ConfigIpCarte>
    </carteAccesDistant>
  </router>
  <cable>
    <type>droit</type>
    <longueur>30</longueur>
    <noeudPointA>1</noeudPointA>
    <portPointA>1</portPointA>
    <noeudPointB>4</noeudPointB>
    <portPointB>1</portPointB>
  </cable>
  <cable>
    <type>droit</type>
    <longueur>30</longueur>
    <noeudPointA>2</noeudPointA>
    <portPointA>1</portPointA>
    <noeudPointB>4</noeudPointB>
    <portPointB>3</portPointB>
  </cable>
  <cable>
    <type>droit</type>
    <longueur>30</longueur>
    <noeudPointA>4</noeudPointA>
    <portPointA>7</portPointA>
    <noeudPointB>5</noeudPointB>
    <portPointB>1</portPointB>
  </cable>
  <cable>
    <type>droit</type>
    <longueur>30</longueur>
    <noeudPointA>6</noeudPointA>
    <portPointA>1</portPointA>
    <noeudPointB>5</noeudPointB>
    <portPointB>2</portPointB>
  </cable>
  <cable>
    <type>droit</type>
    <longueur>30</longueur>
    <noeudPointA>7</noeudPointA>
    <portPointA>1</portPointA>
    <noeudPointB>5</noeudPointB>
    <portPointB>3</portPointB>
  </cable>
  <cable>
    <type>droit</type>
    <longueur>30</longueur>
    <noeudPointA>8</noeudPointA>
    <portPointA>1</portPointA>
    <noeudPointB>5</noeudPointB>
    <portPointB>4</portPointB>
  </cable>
  <cable>
    <type>droit</type>
    <longueur>30</longueur>
    <noeudPointA>9</noeudPointA>
    <portPointA>1</portPointA>
    <noeudPointB>15</noeudPointB>
    <portPointB>1</portPointB>
  </cable>
  <cable>
    <type>droit</type>
    <longueur>30</longueur>
    <noeudPointA>11</noeudPointA>
    <portPointA>1</portPointA>
    <noeudPointB>15</noeudPointB>
    <portPointB>2</portPointB>
  </cable>
  <cable>
    <type>droit</type>
    <longueur>30</longueur>
    <noeudPointA>10</noeudPointA>
    <portPointA>1</portPointA>
    <noeudPointB>14</noeudPointB>
    <portPointB>2</portPointB>
  </cable>
  <cable>
    <type>droit</type>
    <longueur>30</longueur>
    <noeudPointA>5</noeudPointA>
    <portPointA>5</portPointA>
    <noeudPointB>16</noeudPointB>
    <portPointB>1</portPointB>
  </cable>
  <cable>
    <type>droit</type>
    <longueur>30</longueur>
    <noeudPointA>14</noeudPointA>
    <portPointA>4</portPointA>
    <noeudPointB>16</noeudPointB>
    <portPointB>2</portPointB>
  </cable>
  <cable>
    <type>droit</type>
    <longueur>30</longueur>
    <noeudPointA>15</noeudPointA>
    <portPointA>4</portPointA>
    <noeudPointB>16</noeudPointB>
    <portPointB>3</portPointB>
  </cable>
  <cable>
    <type>droit</type>
    <longueur>30</longueur>
    <noeudPointA>14</noeudPointA>
    <portPointA>1</portPointA>
    <noeudPointB>3</noeudPointB>
    <portPointB>1</portPointB>
  </cable>
</simRes>